chub/__init__.py
chub/api.py
chub/handlers.py
chub/oauth2.py
opp_chub-1.0.6.dist-info/DESCRIPTION.rst
opp_chub-1.0.6.dist-info/METADATA
opp_chub-1.0.6.dist-info/RECORD
opp_chub-1.0.6.dist-info/WHEEL
opp_chub-1.0.6.dist-info/metadata.json
opp_chub-1.0.6.dist-info/top_level.txt
