Metadata-Version: 2.0
Name: opp-chub
Version: 1.0.6
Summary: Asynchronous Python client for the Open Permissions Platform Coalition REST Services
Home-page: https://github.com/openpermissions/chub
Author: Open Permissions Platform Coalition
Author-email: support@openpermissions.org
License: Apache 2.0
Platform: UNKNOWN
Classifier: Development Status :: 5 - Production/Stable
Classifier: Intended Audience :: Developers
Classifier: Natural Language :: English
Classifier: License :: OSI Approved :: Apache Software License
Classifier: Programming Language :: Python
Classifier: Programming Language :: Python :: 2.7
Classifier: Programming Language :: Python :: Implementation :: CPython
Requires-Dist: tornado
